MANIFEST.in
README.md
requirements.txt
setup.cfg
setup.py
bin/repostatus
repostatus/__init__.py
repostatus/commit_mgr.py
repostatus/main.py
repostatus/token_generator.py
repostatus.egg-info/PKG-INFO
repostatus.egg-info/SOURCES.txt
repostatus.egg-info/dependency_links.txt
repostatus.egg-info/requires.txt
repostatus.egg-info/top_level.txt