Metadata-Version: 2.1
Name: repostatus
Version: 0.0.3
Summary: Python module for managing github repo status
Home-page: https://avattathil.github.io/repostatus
Author: Tony Vattathil
Author-email: avattathil@gmail.com
License: Apache License 2.0
Download-URL: https://github.com/avattathil/repostatus/tarball/master
Keywords: git,repostatus
Platform: UNKNOWN
Classifier: Development Status :: 2 - Pre-Alpha
Classifier: Intended Audience :: Developers
Classifier: License :: OSI Approved :: Apache Software License
Classifier: Programming Language :: Python :: 3.5
Classifier: Programming Language :: Python :: 3.6
Classifier: Programming Language :: Python :: 3.7
Classifier: Topic :: Software Development :: Libraries
Classifier: Operating System :: POSIX :: Linux
